r3e_api/__init__.py
r3e_api/data.cs
r3e_api/shared_memory.py
r3e_api/data/data.cs
r3e_api-0.1.2.dist-info/METADATA
r3e_api-0.1.2.dist-info/WHEEL
r3e_api-0.1.2.dist-info/top_level.txt
r3e_api-0.1.2.dist-info/RECORD
